{"fetched_at": "2026-07-07T01:16:10+00:00", "events": [{"id": "8708f0b1ad493caa280c8d963be2dc0b", "sport_key": "baseball_mlb", "sport_title": "MLB", "commence_time": "2026-07-06T22:41:00Z", "home_team": "Tampa Bay Rays", "away_team": "New York Yankees", "bookmakers": []}, {"id": "14986526f62254742f296b0eda680507", "sport_key": "baseball_mlb", "sport_title": "MLB", "commence_time": "2026-07-06T22:46:00Z", "home_team": "Washington Nationals", "away_team": "Houston Astros", "bookmakers": []}, {"id": "ceda0420b6aec99d07f85f99472f8c68", "sport_key": "baseball_mlb", "sport_title": "MLB", "commence_time": "2026-07-06T23:16:00Z", "home_team": "Atlanta Braves", "away_team": "New York Mets", "bookmakers": []}, {"id": "e5295ada7ac0d16be6bf67d6a4a2923b", "sport_key": "baseball_mlb", "sport_title": "MLB", "commence_time": "2026-07-06T23:45:11Z", "home_team": "St. Louis Cardinals", "away_team": "Milwaukee Brewers", "bookmakers": [{"key": "williamhill_us", "title": "Caesars", "markets": [{"key": "pitcher_outs", "last_update": "2026-07-07T01:07:54Z", "outcomes": [{"name": "Over", "description": "Shane Drohan", "price": 117, "point": 15.5}, {"name": "Under", "description": "Shane Drohan", "price": -157, "point": 15.5}]}]}, {"key": "draftkings", "title": "DraftKings", "markets": [{"key": "pitcher_earned_runs", "last_update": "2026-07-07T01:14:14Z", "outcomes": [{"name": "Over", "description": "Shane Drohan", "price": 205, "point": 0.5}, {"name": "Under", "description": "Shane Drohan", "price": -285, "point": 0.5}]}, {"key": "pitcher_outs", "last_update": "2026-07-07T01:14:14Z", "outcomes": [{"name": "Over", "description": "Shane Drohan", "price": 120, "point": 15.5}, {"name": "Under", "description": "Shane Drohan", "price": -165, "point": 15.5}]}, {"key": "pitcher_strikeouts", "last_update": "2026-07-07T01:14:14Z", "outcomes": [{"name": "Over", "description": "Shane Drohan", "price": -235, "point": 2.5}, {"name": "Under", "description": "Shane Drohan", "price": 170, "point": 2.5}]}, {"key": "pitcher_walks", "last_update": "2026-07-07T01:14:14Z", "outcomes": [{"name": "Over", "description": "Shane Drohan", "price": 150, "point": 2.5}, {"name": "Under", "description": "Shane Drohan", "price": -205, "point": 2.5}]}]}]}, {"id": "d1ba74caa5492c9e300650c9ba7bebab", "sport_key": "baseball_mlb", "sport_title": "MLB", "commence_time": "2026-07-07T01:41:00Z", "home_team": "San Diego Padres", "away_team": "Arizona Diamondbacks", "bookmakers": [{"key": "fanduel", "title": "FanDuel", "markets": [{"key": "pitcher_outs", "last_update": "2026-07-07T01:15:54Z", "outcomes": [{"name": "Over", "description": "Walker Buehler", "price": 104, "point": 15.5}, {"name": "Under", "description": "Walker Buehler", "price": -140, "point": 15.5}, {"name": "Over", "description": "Brandon Pfaadt", "price": -152, "point": 14.5}, {"name": "Under", "description": "Brandon Pfaadt", "price": 112, "point": 14.5}]}, {"key": "pitcher_strikeouts", "last_update": "2026-07-07T01:15:54Z", "outcomes": [{"name": "Over", "description": "Brandon Pfaadt", "price": -120, "point": 3.5}, {"name": "Under", "description": "Brandon Pfaadt", "price": -106, "point": 3.5}, {"name": "Over", "description": "Walker Buehler", "price": -166, "point": 3.5}, {"name": "Under", "description": "Walker Buehler", "price": 130, "point": 3.5}]}]}, {"key": "fanatics", "title": "Fanatics", "markets": [{"key": "pitcher_earned_runs", "last_update": "2026-07-07T01:14:00Z", "outcomes": [{"name": "Over", "description": "Brandon Pfaadt", "price": 105, "point": 2.5}, {"name": "Under", "description": "Brandon Pfaadt", "price": -150, "point": 2.5}]}, {"key": "pitcher_outs", "last_update": "2026-07-07T01:14:00Z", "outcomes": [{"name": "Over", "description": "Brandon Pfaadt", "price": -150, "point": 14.5}, {"name": "Under", "description": "Brandon Pfaadt", "price": 105, "point": 14.5}]}, {"key": "pitcher_strikeouts", "last_update": "2026-07-07T01:14:00Z", "outcomes": [{"name": "Over", "description": "Brandon Pfaadt", "price": -130, "point": 3.5}, {"name": "Under", "description": "Brandon Pfaadt", "price": 100, "point": 3.5}]}]}, {"key": "betonlineag", "title": "BetOnline.ag", "markets": [{"key": "pitcher_outs", "last_update": "2026-07-07T01:15:53Z", "outcomes": [{"name": "Over", "description": "Walker Buehler", "price": -105, "point": 15.5}, {"name": "Under", "description": "Walker Buehler", "price": -135, "point": 15.5}]}, {"key": "pitcher_strikeouts", "last_update": "2026-07-07T01:15:53Z", "outcomes": [{"name": "Over", "description": "Brandon Pfaadt", "price": -130, "point": 3.5}, {"name": "Under", "description": "Brandon Pfaadt", "price": 100, "point": 3.5}, {"name": "Over", "description": "Walker Buehler", "price": -164, "point": 3.5}, {"name": "Under", "description": "Walker Buehler", "price": 125, "point": 3.5}]}]}, {"key": "williamhill_us", "title": "Caesars", "markets": [{"key": "pitcher_outs", "last_update": "2026-07-07T01:11:20Z", "outcomes": [{"name": "Over", "description": "Walker Buehler", "price": -105, "point": 15.5}, {"name": "Under", "description": "Walker Buehler", "price": -128, "point": 15.5}, {"name": "Over", "description": "Brandon Pfaadt", "price": -150, "point": 14.5}, {"name": "Under", "description": "Brandon Pfaadt", "price": 113, "point": 14.5}]}]}, {"key": "draftkings", "title": "DraftKings", "markets": [{"key": "pitcher_earned_runs", "last_update": "2026-07-07T01:15:51Z", "outcomes": [{"name": "Over", "description": "Walker Buehler", "price": 122, "point": 2.5}, {"name": "Under", "description": "Walker Buehler", "price": -163, "point": 2.5}, {"name": "Over", "description": "Brandon Pfaadt", "price": 113, "point": 2.5}, {"name": "Under", "description": "Brandon Pfaadt", "price": -150, "point": 2.5}]}, {"key": "pitcher_outs", "last_update": "2026-07-07T01:15:51Z", "outcomes": [{"name": "Over", "description": "Walker Buehler", "price": -115, "point": 15.5}, {"name": "Under", "description": "Walker Buehler", "price": -116, "point": 15.5}, {"name": "Over", "description": "Brandon Pfaadt", "price": -146, "point": 14.5}, {"name": "Under", "description": "Brandon Pfaadt", "price": 110, "point": 14.5}]}, {"key": "pitcher_strikeouts", "last_update": "2026-07-07T01:15:51Z", "outcomes": [{"name": "Over", "description": "Walker Buehler", "price": -167, "point": 3.5}, {"name": "Under", "description": "Walker Buehler", "price": 131, "point": 3.5}, {"name": "Over", "description": "Brandon Pfaadt", "price": -120, "point": 3.5}, {"name": "Under", "description": "Brandon Pfaadt", "price": -107, "point": 3.5}]}, {"key": "pitcher_walks", "last_update": "2026-07-07T01:15:51Z", "outcomes": [{"name": "Over", "description": "Brandon Pfaadt", "price": 111, "point": 1.5}, {"name": "Under", "description": "Brandon Pfaadt", "price": -148, "point": 1.5}, {"name": "Over", "description": "Walker Buehler", "price": -183, "point": 1.5}, {"name": "Under", "description": "Walker Buehler", "price": 137, "point": 1.5}]}]}, {"key": "betrivers", "title": "BetRivers", "markets": [{"key": "pitcher_outs", "last_update": "2026-07-07T01:15:51Z", "outcomes": [{"name": "Over", "description": "Brandon Pfaadt", "price": -159, "point": 14.5}, {"name": "Over", "description": "Walker Buehler", "price": -115, "point": 15.5}]}, {"key": "pitcher_strikeouts", "last_update": "2026-07-07T01:15:51Z", "outcomes": [{"name": "Over", "description": "Walker Buehler", "price": -139, "point": 3.5}, {"name": "Under", "description": "Walker Buehler", "price": 105, "point": 3.5}, {"name": "Over", "description": "Brandon Pfaadt", "price": -127, "point": 3.5}, {"name": "Under", "description": "Brandon Pfaadt", "price": -106, "point": 3.5}]}]}, {"key": "betmgm", "title": "BetMGM", "markets": [{"key": "pitcher_earned_runs", "last_update": "2026-07-07T01:15:49Z", "outcomes": [{"name": "Over", "description": "Brandon Pfaadt", "price": 110, "point": 2.5}, {"name": "Under", "description": "Brandon Pfaadt", "price": -150, "point": 2.5}, {"name": "Over", "description": "Walker Buehler", "price": 115, "point": 2.5}, {"name": "Under", "description": "Walker Buehler", "price": -155, "point": 2.5}]}, {"key": "pitcher_outs", "last_update": "2026-07-07T01:15:49Z", "outcomes": [{"name": "Over", "description": "Brandon Pfaadt", "price": -150, "point": 14.5}, {"name": "Under", "description": "Brandon Pfaadt", "price": 110, "point": 14.5}, {"name": "Over", "description": "Walker Buehler", "price": -110, "point": 15.5}, {"name": "Under", "description": "Walker Buehler", "price": -120, "point": 15.5}]}, {"key": "pitcher_strikeouts", "last_update": "2026-07-07T01:15:49Z", "outcomes": [{"name": "Over", "description": "Walker Buehler", "price": -155, "point": 3.5}, {"name": "Under", "description": "Walker Buehler", "price": 115, "point": 3.5}, {"name": "Over", "description": "Brandon Pfaadt", "price": -150, "point": 3.5}, {"name": "Under", "description": "Brandon Pfaadt", "price": 110, "point": 3.5}]}]}, {"key": "bovada", "title": "Bovada", "markets": [{"key": "pitcher_outs", "last_update": "2026-07-07T01:15:07Z", "outcomes": [{"name": "Over", "description": "Brandon Pfaadt", "price": -140, "point": 14.5}, {"name": "Under", "description": "Brandon Pfaadt", "price": 100, "point": 14.5}, {"name": "Over", "description": "Walker Buehler", "price": -120, "point": 15.5}, {"name": "Under", "description": "Walker Buehler", "price": -120, "point": 15.5}]}, {"key": "pitcher_strikeouts", "last_update": "2026-07-07T01:15:07Z", "outcomes": [{"name": "Over", "description": "Brandon Pfaadt", "price": -120, "point": 3.5}, {"name": "Under", "description": "Brandon Pfaadt", "price": -110, "point": 3.5}, {"name": "Over", "description": "Walker Buehler", "price": -170, "point": 3.5}, {"name": "Under", "description": "Walker Buehler", "price": 130, "point": 3.5}]}, {"key": "pitcher_walks", "last_update": "2026-07-07T01:15:07Z", "outcomes": [{"name": "Over", "description": "Brandon Pfaadt", "price": 110, "point": 1.5}, {"name": "Under", "description": "Brandon Pfaadt", "price": -150, "point": 1.5}, {"name": "Over", "description": "Walker Buehler", "price": -180, "point": 1.5}, {"name": "Under", "description": "Walker Buehler", "price": 140, "point": 1.5}]}]}]}, {"id": "92bad434cf32ec6dd5e2b856708a6596", "sport_key": "baseball_mlb", "sport_title": "MLB", "commence_time": "2026-07-07T01:46:00Z", "home_team": "San Francisco Giants", "away_team": "Toronto Blue Jays", "bookmakers": [{"key": "fanduel", "title": "FanDuel", "markets": [{"key": "pitcher_outs", "last_update": "2026-07-07T01:15:45Z", "outcomes": [{"name": "Over", "description": "Kevin Gausman", "price": -152, "point": 17.5}, {"name": "Under", "description": "Kevin Gausman", "price": 114, "point": 17.5}, {"name": "Over", "description": "Landen Roupp", "price": 104, "point": 17.5}, {"name": "Under", "description": "Landen Roupp", "price": -140, "point": 17.5}]}, {"key": "pitcher_strikeouts", "last_update": "2026-07-07T01:15:45Z", "outcomes": [{"name": "Over", "description": "Landen Roupp", "price": -162, "point": 4.5}, {"name": "Under", "description": "Landen Roupp", "price": 128, "point": 4.5}, {"name": "Over", "description": "Kevin Gausman", "price": 104, "point": 5.5}, {"name": "Under", "description": "Kevin Gausman", "price": -132, "point": 5.5}]}]}, {"key": "betonlineag", "title": "BetOnline.ag", "markets": [{"key": "pitcher_outs", "last_update": "2026-07-07T01:15:16Z", "outcomes": [{"name": "Over", "description": "Kevin Gausman", "price": -150, "point": 17.5}, {"name": "Under", "description": "Kevin Gausman", "price": 110, "point": 17.5}, {"name": "Over", "description": "Landen Roupp", "price": 100, "point": 17.5}, {"name": "Under", "description": "Landen Roupp", "price": -140, "point": 17.5}]}, {"key": "pitcher_strikeouts", "last_update": "2026-07-07T01:15:16Z", "outcomes": [{"name": "Over", "description": "Kevin Gausman", "price": 110, "point": 5.5}, {"name": "Under", "description": "Kevin Gausman", "price": -143, "point": 5.5}, {"name": "Over", "description": "Landen Roupp", "price": 125, "point": 5.5}, {"name": "Under", "description": "Landen Roupp", "price": -164, "point": 5.5}]}]}, {"key": "williamhill_us", "title": "Caesars", "markets": [{"key": "pitcher_outs", "last_update": "2026-07-07T01:10:37Z", "outcomes": [{"name": "Over", "description": "Landen Roupp", "price": 100, "point": 17.5}, {"name": "Under", "description": "Landen Roupp", "price": -130, "point": 17.5}, {"name": "Over", "description": "Kevin Gausman", "price": -145, "point": 17.5}, {"name": "Under", "description": "Kevin Gausman", "price": 111, "point": 17.5}]}]}, {"key": "betmgm", "title": "BetMGM", "markets": [{"key": "pitcher_earned_runs", "last_update": "2026-07-07T01:15:27Z", "outcomes": [{"name": "Over", "description": "Kevin Gausman", "price": 100, "point": 2.5}, {"name": "Under", "description": "Kevin Gausman", "price": -135, "point": 2.5}, {"name": "Over", "description": "Landen Roupp", "price": 115, "point": 2.5}, {"name": "Under", "description": "Landen Roupp", "price": -155, "point": 2.5}]}, {"key": "pitcher_outs", "last_update": "2026-07-07T01:15:27Z", "outcomes": [{"name": "Over", "description": "Kevin Gausman", "price": -155, "point": 17.5}, {"name": "Under", "description": "Kevin Gausman", "price": 115, "point": 17.5}, {"name": "Over", "description": "Landen Roupp", "price": -125, "point": 17.5}, {"name": "Under", "description": "Landen Roupp", "price": -110, "point": 17.5}]}, {"key": "pitcher_strikeouts", "last_update": "2026-07-07T01:15:27Z", "outcomes": [{"name": "Over", "description": "Landen Roupp", "price": 135, "point": 5.5}, {"name": "Under", "description": "Landen Roupp", "price": -185, "point": 5.5}, {"name": "Over", "description": "Kevin Gausman", "price": 100, "point": 5.5}, {"name": "Under", "description": "Kevin Gausman", "price": -135, "point": 5.5}]}]}, {"key": "draftkings", "title": "DraftKings", "markets": [{"key": "pitcher_earned_runs", "last_update": "2026-07-07T01:15:57Z", "outcomes": [{"name": "Over", "description": "Landen Roupp", "price": 127, "point": 2.5}, {"name": "Under", "description": "Landen Roupp", "price": -169, "point": 2.5}, {"name": "Over", "description": "Kevin Gausman", "price": 111, "point": 2.5}, {"name": "Under", "description": "Kevin Gausman", "price": -148, "point": 2.5}]}, {"key": "pitcher_outs", "last_update": "2026-07-07T01:15:57Z", "outcomes": [{"name": "Over", "description": "Kevin Gausman", "price": -161, "point": 17.5}, {"name": "Under", "description": "Kevin Gausman", "price": 121, "point": 17.5}, {"name": "Over", "description": "Landen Roupp", "price": -106, "point": 17.5}, {"name": "Under", "description": "Landen Roupp", "price": -126, "point": 17.5}]}, {"key": "pitcher_strikeouts", "last_update": "2026-07-07T01:15:57Z", "outcomes": [{"name": "Over", "description": "Kevin Gausman", "price": 100, "point": 5.5}, {"name": "Under", "description": "Kevin Gausman", "price": -127, "point": 5.5}, {"name": "Over", "description": "Landen Roupp", "price": -143, "point": 4.5}, {"name": "Under", "description": "Landen Roupp", "price": 112, "point": 4.5}]}, {"key": "pitcher_walks", "last_update": "2026-07-07T01:15:57Z", "outcomes": [{"name": "Over", "description": "Kevin Gausman", "price": -106, "point": 1.5}, {"name": "Under", "description": "Kevin Gausman", "price": -125, "point": 1.5}, {"name": "Over", "description": "Landen Roupp", "price": -185, "point": 1.5}, {"name": "Under", "description": "Landen Roupp", "price": 138, "point": 1.5}]}]}, {"key": "fanatics", "title": "Fanatics", "markets": [{"key": "pitcher_earned_runs", "last_update": "2026-07-07T01:15:40Z", "outcomes": [{"name": "Over", "description": "Kevin Gausman", "price": -105, "point": 2.5}, {"name": "Under", "description": "Kevin Gausman", "price": -135, "point": 2.5}]}, {"key": "pitcher_outs", "last_update": "2026-07-07T01:15:40Z", "outcomes": [{"name": "Over", "description": "Landen Roupp", "price": -120, "point": 17.5}, {"name": "Under", "description": "Landen Roupp", "price": -120, "point": 17.5}]}, {"key": "pitcher_strikeouts", "last_update": "2026-07-07T01:15:40Z", "outcomes": [{"name": "Over", "description": "Kevin Gausman", "price": 105, "point": 5.5}, {"name": "Under", "description": "Kevin Gausman", "price": -140, "point": 5.5}]}]}, {"key": "bovada", "title": "Bovada", "markets": [{"key": "pitcher_outs", "last_update": "2026-07-07T01:15:22Z", "outcomes": [{"name": "Over", "description": "Kevin Gausman", "price": -160, "point": 17.5}, {"name": "Under", "description": "Kevin Gausman", "price": 120, "point": 17.5}, {"name": "Over", "description": "Landen Roupp", "price": -120, "point": 17.5}, {"name": "Under", "description": "Landen Roupp", "price": -120, "point": 17.5}]}, {"key": "pitcher_strikeouts", "last_update": "2026-07-07T01:15:22Z", "outcomes": [{"name": "Over", "description": "Kevin Gausman", "price": 105, "point": 5.5}, {"name": "Under", "description": "Kevin Gausman", "price": -135, "point": 5.5}, {"name": "Over", "description": "Landen Roupp", "price": -180, "point": 4.5}, {"name": "Under", "description": "Landen Roupp", "price": 135, "point": 4.5}]}, {"key": "pitcher_walks", "last_update": "2026-07-07T01:15:22Z", "outcomes": [{"name": "Over", "description": "Kevin Gausman", "price": -110, "point": 1.5}, {"name": "Under", "description": "Kevin Gausman", "price": -130, "point": 1.5}, {"name": "Over", "description": "Landen Roupp", "price": -180, "point": 1.5}, {"name": "Under", "description": "Landen Roupp", "price": 140, "point": 1.5}]}]}, {"key": "betrivers", "title": "BetRivers", "markets": [{"key": "pitcher_outs", "last_update": "2026-07-07T01:15:44Z", "outcomes": [{"name": "Over", "description": "Kevin Gausman", "price": -167, "point": 17.5}, {"name": "Over", "description": "Landen Roupp", "price": -129, "point": 16.5}]}, {"key": "pitcher_strikeouts", "last_update": "2026-07-07T01:15:44Z", "outcomes": [{"name": "Over", "description": "Kevin Gausman", "price": -107, "point": 5.5}, {"name": "Under", "description": "Kevin Gausman", "price": -125, "point": 5.5}, {"name": "Over", "description": "Landen Roupp", "price": -157, "point": 4.5}, {"name": "Under", "description": "Landen Roupp", "price": 118, "point": 4.5}]}]}]}, {"id": "ce47831dfdb0f68ba311fd79cc19d68a", "sport_key": "baseball_mlb", "sport_title": "MLB", "commence_time": "2026-07-07T02:11:00Z", "home_team": "Los Angeles Dodgers", "away_team": "Colorado Rockies", "bookmakers": [{"key": "fanduel", "title": "FanDuel", "markets": [{"key": "pitcher_outs", "last_update": "2026-07-07T01:15:35Z", "outcomes": [{"name": "Over", "description": "Kyle Freeland", "price": -125, "point": 15.5}, {"name": "Under", "description": "Kyle Freeland", "price": -106, "point": 15.5}, {"name": "Over", "description": "Eric Lauer", "price": -122, "point": 17.5}, {"name": "Under", "description": "Eric Lauer", "price": -108, "point": 17.5}]}, {"key": "pitcher_strikeouts", "last_update": "2026-07-07T01:15:35Z", "outcomes": [{"name": "Over", "description": "Kyle Freeland", "price": 120, "point": 4.5}, {"name": "Under", "description": "Kyle Freeland", "price": -154, "point": 4.5}, {"name": "Over", "description": "Eric Lauer", "price": 100, "point": 4.5}, {"name": "Under", "description": "Eric Lauer", "price": -128, "point": 4.5}]}]}, {"key": "fanatics", "title": "Fanatics", "markets": [{"key": "pitcher_earned_runs", "last_update": "2026-07-07T01:15:14Z", "outcomes": [{"name": "Over", "description": "Kyle Freeland", "price": 100, "point": 3.5}, {"name": "Under", "description": "Kyle Freeland", "price": -140, "point": 3.5}]}, {"key": "pitcher_outs", "last_update": "2026-07-07T01:15:14Z", "outcomes": [{"name": "Over", "description": "Eric Lauer", "price": -130, "point": 17.5}, {"name": "Under", "description": "Eric Lauer", "price": -110, "point": 17.5}]}, {"key": "pitcher_strikeouts", "last_update": "2026-07-07T01:15:14Z", "outcomes": [{"name": "Over", "description": "Kyle Freeland", "price": 115, "point": 4.5}, {"name": "Under", "description": "Kyle Freeland", "price": -150, "point": 4.5}]}]}, {"key": "betonlineag", "title": "BetOnline.ag", "markets": [{"key": "pitcher_outs", "last_update": "2026-07-07T01:15:06Z", "outcomes": [{"name": "Over", "description": "Kyle Freeland", "price": -130, "point": 15.5}, {"name": "Under", "description": "Kyle Freeland", "price": -110, "point": 15.5}, {"name": "Over", "description": "Eric Lauer", "price": -125, "point": 17.5}, {"name": "Under", "description": "Eric Lauer", "price": -115, "point": 17.5}]}, {"key": "pitcher_strikeouts", "last_update": "2026-07-07T01:15:06Z", "outcomes": [{"name": "Over", "description": "Kyle Freeland", "price": 117, "point": 4.5}, {"name": "Under", "description": "Kyle Freeland", "price": -152, "point": 4.5}, {"name": "Over", "description": "Eric Lauer", "price": 120, "point": 4.5}, {"name": "Under", "description": "Eric Lauer", "price": -156, "point": 4.5}]}]}, {"key": "draftkings", "title": "DraftKings", "markets": [{"key": "pitcher_earned_runs", "last_update": "2026-07-07T01:15:10Z", "outcomes": [{"name": "Over", "description": "Eric Lauer", "price": -127, "point": 2.5}, {"name": "Under", "description": "Eric Lauer", "price": -105, "point": 2.5}, {"name": "Over", "description": "Kyle Freeland", "price": 103, "point": 3.5}, {"name": "Under", "description": "Kyle Freeland", "price": -137, "point": 3.5}]}, {"key": "pitcher_outs", "last_update": "2026-07-07T01:15:10Z", "outcomes": [{"name": "Over", "description": "Eric Lauer", "price": -131, "point": 17.5}, {"name": "Under", "description": "Eric Lauer", "price": -102, "point": 17.5}, {"name": "Over", "description": "Kyle Freeland", "price": -123, "point": 15.5}, {"name": "Under", "description": "Kyle Freeland", "price": -108, "point": 15.5}]}, {"key": "pitcher_strikeouts", "last_update": "2026-07-07T01:15:10Z", "outcomes": [{"name": "Over", "description": "Eric Lauer", "price": -101, "point": 4.5}, {"name": "Under", "description": "Eric Lauer", "price": -126, "point": 4.5}, {"name": "Over", "description": "Kyle Freeland", "price": 120, "point": 4.5}, {"name": "Under", "description": "Kyle Freeland", "price": -153, "point": 4.5}]}, {"key": "pitcher_walks", "last_update": "2026-07-07T01:15:10Z", "outcomes": [{"name": "Over", "description": "Eric Lauer", "price": 157, "point": 1.5}, {"name": "Under", "description": "Eric Lauer", "price": -211, "point": 1.5}, {"name": "Over", "description": "Kyle Freeland", "price": 103, "point": 1.5}, {"name": "Under", "description": "Kyle Freeland", "price": -137, "point": 1.5}]}]}, {"key": "williamhill_us", "title": "Caesars", "markets": [{"key": "pitcher_outs", "last_update": "2026-07-07T01:11:29Z", "outcomes": [{"name": "Over", "description": "Eric Lauer", "price": -120, "point": 17.5}, {"name": "Under", "description": "Eric Lauer", "price": -112, "point": 17.5}, {"name": "Over", "description": "Kyle Freeland", "price": -122, "point": 15.5}, {"name": "Under", "description": "Kyle Freeland", "price": -108, "point": 15.5}]}]}, {"key": "betrivers", "title": "BetRivers", "markets": [{"key": "pitcher_outs", "last_update": "2026-07-07T01:15:20Z", "outcomes": [{"name": "Over", "description": "Eric Lauer", "price": -117, "point": 17.5}, {"name": "Over", "description": "Kyle Freeland", "price": -129, "point": 15.5}]}, {"key": "pitcher_strikeouts", "last_update": "2026-07-07T01:15:20Z", "outcomes": [{"name": "Over", "description": "Eric Lauer", "price": 108, "point": 4.5}, {"name": "Under", "description": "Eric Lauer", "price": -143, "point": 4.5}, {"name": "Over", "description": "Kyle Freeland", "price": -167, "point": 3.5}, {"name": "Under", "description": "Kyle Freeland", "price": 125, "point": 3.5}]}]}, {"key": "betmgm", "title": "BetMGM", "markets": [{"key": "pitcher_earned_runs", "last_update": "2026-07-07T01:15:25Z", "outcomes": [{"name": "Over", "description": "Kyle Freeland", "price": 100, "point": 3.5}, {"name": "Under", "description": "Kyle Freeland", "price": -140, "point": 3.5}, {"name": "Over", "description": "Eric Lauer", "price": -120, "point": 2.5}, {"name": "Under", "description": "Eric Lauer", "price": -110, "point": 2.5}]}, {"key": "pitcher_outs", "last_update": "2026-07-07T01:15:25Z", "outcomes": [{"name": "Over", "description": "Kyle Freeland", "price": -125, "point": 16.5}, {"name": "Under", "description": "Kyle Freeland", "price": -110, "point": 16.5}, {"name": "Over", "description": "Eric Lauer", "price": -118, "point": 17.5}, {"name": "Under", "description": "Eric Lauer", "price": -115, "point": 17.5}]}, {"key": "pitcher_strikeouts", "last_update": "2026-07-07T01:15:25Z", "outcomes": [{"name": "Over", "description": "Kyle Freeland", "price": -185, "point": 3.5}, {"name": "Under", "description": "Kyle Freeland", "price": 135, "point": 3.5}, {"name": "Over", "description": "Eric Lauer", "price": -200, "point": 3.5}, {"name": "Under", "description": "Eric Lauer", "price": 145, "point": 3.5}]}]}, {"key": "bovada", "title": "Bovada", "markets": [{"key": "pitcher_earned_runs", "last_update": "2026-07-07T01:15:51Z", "outcomes": [{"name": "Over", "description": "Eric Lauer", "price": -135, "point": 2.5}, {"name": "Under", "description": "Eric Lauer", "price": -105, "point": 2.5}, {"name": "Over", "description": "Kyle Freeland", "price": -105, "point": 3.5}, {"name": "Under", "description": "Kyle Freeland", "price": -135, "point": 3.5}]}, {"key": "pitcher_outs", "last_update": "2026-07-07T01:15:51Z", "outcomes": [{"name": "Over", "description": "Eric Lauer", "price": -135, "point": 17.5}, {"name": "Under", "description": "Eric Lauer", "price": -105, "point": 17.5}, {"name": "Over", "description": "Kyle Freeland", "price": -125, "point": 15.5}, {"name": "Under", "description": "Kyle Freeland", "price": -115, "point": 15.5}]}, {"key": "pitcher_strikeouts", "last_update": "2026-07-07T01:15:51Z", "outcomes": [{"name": "Over", "description": "Eric Lauer", "price": 110, "point": 4.5}, {"name": "Under", "description": "Eric Lauer", "price": -145, "point": 4.5}, {"name": "Over", "description": "Kyle Freeland", "price": 120, "point": 4.5}, {"name": "Under", "description": "Kyle Freeland", "price": -160, "point": 4.5}]}, {"key": "pitcher_walks", "last_update": "2026-07-07T01:15:51Z", "outcomes": [{"name": "Over", "description": "Eric Lauer", "price": 155, "point": 1.5}, {"name": "Under", "description": "Eric Lauer", "price": -220, "point": 1.5}, {"name": "Over", "description": "Kyle Freeland", "price": 100, "point": 1.5}, {"name": "Under", "description": "Kyle Freeland", "price": -140, "point": 1.5}]}]}]}, {"id": "6611ecd500747b1f1aebe1ea49f9d00a", "sport_key": "baseball_mlb", "sport_title": "MLB", "commence_time": "2026-07-07T18:16:00Z", "home_team": "St. Louis Cardinals", "away_team": "Milwaukee Brewers", "bookmakers": []}, {"id": "a250fe250560caa8b56cd4e061c8e7b0", "sport_key": "baseball_mlb", "sport_title": "MLB", "commence_time": "2026-07-07T22:36:00Z", "home_team": "Baltimore Orioles", "away_team": "Chicago Cubs", "bookmakers": [{"key": "fanduel", "title": "FanDuel", "markets": [{"key": "pitcher_strikeouts", "last_update": "2026-07-07T01:15:56Z", "outcomes": [{"name": "Over", "description": "Matthew Boyd", "price": -156, "point": 4.5}, {"name": "Under", "description": "Matthew Boyd", "price": 122, "point": 4.5}, {"name": "Over", "description": "Shane Baz", "price": -102, "point": 5.5}, {"name": "Under", "description": "Shane Baz", "price": -125, "point": 5.5}]}]}, {"key": "fanatics", "title": "Fanatics", "markets": [{"key": "pitcher_earned_runs", "last_update": "2026-07-07T01:15:04Z", "outcomes": [{"name": "Over", "description": "Matthew Boyd", "price": 105, "point": 2.5}, {"name": "Under", "description": "Matthew Boyd", "price": -150, "point": 2.5}]}, {"key": "pitcher_strikeouts", "last_update": "2026-07-07T01:15:04Z", "outcomes": [{"name": "Over", "description": "Matthew Boyd", "price": -165, "point": 4.5}, {"name": "Under", "description": "Matthew Boyd", "price": 125, "point": 4.5}]}]}, {"key": "draftkings", "title": "DraftKings", "markets": [{"key": "pitcher_strikeouts", "last_update": "2026-07-07T01:15:47Z", "outcomes": [{"name": "Over", "description": "Shane Baz", "price": 106, "point": 5.5}, {"name": "Under", "description": "Shane Baz", "price": -136, "point": 5.5}, {"name": "Over", "description": "Matthew Boyd", "price": 129, "point": 5.5}, {"name": "Under", "description": "Matthew Boyd", "price": -165, "point": 5.5}]}]}, {"key": "bovada", "title": "Bovada", "markets": [{"key": "pitcher_earned_runs", "last_update": "2026-07-07T01:15:40Z", "outcomes": [{"name": "Over", "description": "Matthew Boyd", "price": 110, "point": 2.5}, {"name": "Under", "description": "Matthew Boyd", "price": -150, "point": 2.5}, {"name": "Over", "description": "Shane Baz", "price": -125, "point": 2.5}, {"name": "Under", "description": "Shane Baz", "price": -115, "point": 2.5}]}, {"key": "pitcher_strikeouts", "last_update": "2026-07-07T01:15:40Z", "outcomes": [{"name": "Over", "description": "Matthew Boyd", "price": -160, "point": 4.5}, {"name": "Under", "description": "Matthew Boyd", "price": 120, "point": 4.5}, {"name": "Over", "description": "Shane Baz", "price": -105, "point": 5.5}, {"name": "Under", "description": "Shane Baz", "price": -125, "point": 5.5}]}]}]}, {"id": "c892fb37a2662fa901742b27c6b7f205", "sport_key": "baseball_mlb", "sport_title": "MLB", "commence_time": "2026-07-07T22:41:00Z", "home_team": "Detroit Tigers", "away_team": "Athletics", "bookmakers": [{"key": "fanduel", "title": "FanDuel", "markets": [{"key": "pitcher_strikeouts", "last_update": "2026-07-07T01:15:37Z", "outcomes": [{"name": "Over", "description": "Tarik Skubal", "price": 114, "point": 8.5}, {"name": "Under", "description": "Tarik Skubal", "price": -146, "point": 8.5}, {"name": "Over", "description": "JT Ginn", "price": -180, "point": 4.5}, {"name": "Under", "description": "JT Ginn", "price": 140, "point": 4.5}]}]}, {"key": "fanatics", "title": "Fanatics", "markets": [{"key": "pitcher_earned_runs", "last_update": "2026-07-07T01:15:58Z", "outcomes": [{"name": "Over", "description": "Tarik Skubal", "price": -125, "point": 1.5}, {"name": "Under", "description": "Tarik Skubal", "price": -115, "point": 1.5}]}, {"key": "pitcher_outs", "last_update": "2026-07-07T01:15:58Z", "outcomes": [{"name": "Over", "description": "Tarik Skubal", "price": 125, "point": 18.5}, {"name": "Under", "description": "Tarik Skubal", "price": -180, "point": 18.5}]}, {"key": "pitcher_strikeouts", "last_update": "2026-07-07T01:15:58Z", "outcomes": [{"name": "Over", "description": "JT Ginn", "price": 115, "point": 5.5}, {"name": "Under", "description": "JT Ginn", "price": -150, "point": 5.5}]}]}, {"key": "draftkings", "title": "DraftKings", "markets": [{"key": "pitcher_outs", "last_update": "2026-07-07T01:15:50Z", "outcomes": [{"name": "Over", "description": "Tarik Skubal", "price": -185, "point": 17.5}, {"name": "Under", "description": "Tarik Skubal", "price": 138, "point": 17.5}, {"name": "Over", "description": "JT Ginn", "price": -127, "point": 16.5}, {"name": "Under", "description": "JT Ginn", "price": -104, "point": 16.5}]}, {"key": "pitcher_strikeouts", "last_update": "2026-07-07T01:15:50Z", "outcomes": [{"name": "Over", "description": "Tarik Skubal", "price": 101, "point": 8.5}, {"name": "Under", "description": "Tarik Skubal", "price": -129, "point": 8.5}, {"name": "Over", "description": "JT Ginn", "price": 119, "point": 5.5}, {"name": "Under", "description": "JT Ginn", "price": -152, "point": 5.5}]}]}, {"key": "bovada", "title": "Bovada", "markets": [{"key": "pitcher_earned_runs", "last_update": "2026-07-07T01:15:47Z", "outcomes": [{"name": "Over", "description": "JT Ginn", "price": -125, "point": 2.5}, {"name": "Under", "description": "JT Ginn", "price": -115, "point": 2.5}, {"name": "Over", "description": "Tarik Skubal", "price": -125, "point": 1.5}, {"name": "Under", "description": "Tarik Skubal", "price": -115, "point": 1.5}]}, {"key": "pitcher_outs", "last_update": "2026-07-07T01:15:47Z", "outcomes": [{"name": "Over", "description": "JT Ginn", "price": -135, "point": 16.5}, {"name": "Under", "description": "JT Ginn", "price": -105, "point": 16.5}, {"name": "Over", "description": "Tarik Skubal", "price": -180, "point": 17.5}, {"name": "Under", "description": "Tarik Skubal", "price": 140, "point": 17.5}]}, {"key": "pitcher_strikeouts", "last_update": "2026-07-07T01:15:47Z", "outcomes": [{"name": "Over", "description": "JT Ginn", "price": -185, "point": 4.5}, {"name": "Under", "description": "JT Ginn", "price": 140, "point": 4.5}, {"name": "Over", "description": "Tarik Skubal", "price": 115, "point": 8.5}, {"name": "Under", "description": "Tarik Skubal", "price": -150, "point": 8.5}]}]}]}, {"id": "e38e52ed47e9148a67603013c94f7295", "sport_key": "baseball_mlb", "sport_title": "MLB", "commence_time": "2026-07-07T22:41:00Z", "home_team": "Pittsburgh Pirates", "away_team": "Atlanta Braves", "bookmakers": [{"key": "fanduel", "title": "FanDuel", "markets": [{"key": "pitcher_strikeouts", "last_update": "2026-07-07T01:15:47Z", "outcomes": [{"name": "Over", "description": "Paul Skenes", "price": -132, "point": 6.5}, {"name": "Under", "description": "Paul Skenes", "price": 104, "point": 6.5}, {"name": "Over", "description": "Hurston Waldrep", "price": -102, "point": 4.5}, {"name": "Under", "description": "Hurston Waldrep", "price": -125, "point": 4.5}]}]}]}, {"id": "157306fb8124249fa8e55016561ce711", "sport_key": "baseball_mlb", "sport_title": "MLB", "commence_time": "2026-07-07T22:41:00Z", "home_team": "Miami Marlins", "away_team": "Seattle Mariners", "bookmakers": []}, {"id": "e3cd1f3a8c40c74e867b7713af7e6365", "sport_key": "baseball_mlb", "sport_title": "MLB", "commence_time": "2026-07-07T22:41:00Z", "home_team": "Tampa Bay Rays", "away_team": "New York Yankees", "bookmakers": []}, {"id": "a11dc5b41df437e869c4abe72abced1f", "sport_key": "baseball_mlb", "sport_title": "MLB", "commence_time": "2026-07-07T22:46:00Z", "home_team": "Washington Nationals", "away_team": "Houston Astros", "bookmakers": [{"key": "fanduel", "title": "FanDuel", "markets": [{"key": "pitcher_strikeouts", "last_update": "2026-07-07T01:15:51Z", "outcomes": [{"name": "Over", "description": "Andrew Alvarez", "price": -106, "point": 4.5}, {"name": "Under", "description": "Andrew Alvarez", "price": -120, "point": 4.5}, {"name": "Over", "description": "Tatsuya Imai", "price": -148, "point": 4.5}, {"name": "Under", "description": "Tatsuya Imai", "price": 116, "point": 4.5}]}]}]}, {"id": "288b4514ed237def0df905ead634d530", "sport_key": "baseball_mlb", "sport_title": "MLB", "commence_time": "2026-07-07T23:11:00Z", "home_team": "New York Mets", "away_team": "Kansas City Royals", "bookmakers": []}, {"id": "fa63ecda3e7fe4b049c7e9cfd633f461", "sport_key": "baseball_mlb", "sport_title": "MLB", "commence_time": "2026-07-07T23:41:00Z", "home_team": "Chicago White Sox", "away_team": "Boston Red Sox", "bookmakers": [{"key": "fanduel", "title": "FanDuel", "markets": [{"key": "pitcher_strikeouts", "last_update": "2026-07-07T01:15:37Z", "outcomes": [{"name": "Over", "description": "Payton Tolle", "price": -115, "point": 5.5}, {"name": "Under", "description": "Payton Tolle", "price": -111, "point": 5.5}, {"name": "Over", "description": "Noah Schultz", "price": -128, "point": 4.5}, {"name": "Under", "description": "Noah Schultz", "price": 100, "point": 4.5}]}]}, {"key": "fanatics", "title": "Fanatics", "markets": [{"key": "pitcher_earned_runs", "last_update": "2026-07-07T01:15:26Z", "outcomes": [{"name": "Over", "description": "Noah Schultz", "price": 100, "point": 2.5}, {"name": "Under", "description": "Noah Schultz", "price": -140, "point": 2.5}]}, {"key": "pitcher_outs", "last_update": "2026-07-07T01:15:26Z", "outcomes": [{"name": "Over", "description": "Noah Schultz", "price": -155, "point": 14.5}, {"name": "Under", "description": "Noah Schultz", "price": 110, "point": 14.5}]}, {"key": "pitcher_strikeouts", "last_update": "2026-07-07T01:15:26Z", "outcomes": [{"name": "Over", "description": "Payton Tolle", "price": -130, "point": 5.5}, {"name": "Under", "description": "Payton Tolle", "price": 100, "point": 5.5}]}]}, {"key": "draftkings", "title": "DraftKings", "markets": [{"key": "pitcher_outs", "last_update": "2026-07-07T01:15:55Z", "outcomes": [{"name": "Over", "description": "Payton Tolle", "price": -104, "point": 17.5}, {"name": "Under", "description": "Payton Tolle", "price": -128, "point": 17.5}, {"name": "Over", "description": "Noah Schultz", "price": -157, "point": 14.5}, {"name": "Under", "description": "Noah Schultz", "price": 118, "point": 14.5}]}, {"key": "pitcher_strikeouts", "last_update": "2026-07-07T01:15:55Z", "outcomes": [{"name": "Over", "description": "Payton Tolle", "price": -132, "point": 5.5}, {"name": "Under", "description": "Payton Tolle", "price": 104, "point": 5.5}, {"name": "Over", "description": "Noah Schultz", "price": -143, "point": 4.5}, {"name": "Under", "description": "Noah Schultz", "price": 112, "point": 4.5}]}]}, {"key": "bovada", "title": "Bovada", "markets": [{"key": "pitcher_earned_runs", "last_update": "2026-07-07T01:15:35Z", "outcomes": [{"name": "Over", "description": "Noah Schultz", "price": 100, "point": 2.5}, {"name": "Under", "description": "Noah Schultz", "price": -140, "point": 2.5}, {"name": "Over", "description": "Payton Tolle", "price": 115, "point": 2.5}, {"name": "Under", "description": "Payton Tolle", "price": -155, "point": 2.5}]}, {"key": "pitcher_outs", "last_update": "2026-07-07T01:15:35Z", "outcomes": [{"name": "Over", "description": "Noah Schultz", "price": -160, "point": 14.5}, {"name": "Under", "description": "Noah Schultz", "price": 120, "point": 14.5}, {"name": "Over", "description": "Payton Tolle", "price": -105, "point": 17.5}, {"name": "Under", "description": "Payton Tolle", "price": -135, "point": 17.5}]}, {"key": "pitcher_strikeouts", "last_update": "2026-07-07T01:15:35Z", "outcomes": [{"name": "Over", "description": "Noah Schultz", "price": -130, "point": 4.5}, {"name": "Under", "description": "Noah Schultz", "price": 100, "point": 4.5}, {"name": "Over", "description": "Payton Tolle", "price": -115, "point": 5.5}, {"name": "Under", "description": "Payton Tolle", "price": -115, "point": 5.5}]}]}]}, {"id": "a21ff3f3e886298451df6978c4be743c", "sport_key": "baseball_mlb", "sport_title": "MLB", "commence_time": "2026-07-07T23:41:00Z", "home_team": "Minnesota Twins", "away_team": "Cleveland Guardians", "bookmakers": [{"key": "fanduel", "title": "FanDuel", "markets": [{"key": "pitcher_strikeouts", "last_update": "2026-07-07T01:15:50Z", "outcomes": [{"name": "Over", "description": "Taj Bradley", "price": 120, "point": 6.5}, {"name": "Under", "description": "Taj Bradley", "price": -154, "point": 6.5}, {"name": "Over", "description": "Joey Cantillo", "price": -166, "point": 4.5}, {"name": "Under", "description": "Joey Cantillo", "price": 130, "point": 4.5}]}]}, {"key": "fanatics", "title": "Fanatics", "markets": [{"key": "pitcher_earned_runs", "last_update": "2026-07-07T01:15:27Z", "outcomes": [{"name": "Over", "description": "Joey Cantillo", "price": -105, "point": 2.5}, {"name": "Under", "description": "Joey Cantillo", "price": -135, "point": 2.5}]}, {"key": "pitcher_outs", "last_update": "2026-07-07T01:15:27Z", "outcomes": [{"name": "Over", "description": "Joey Cantillo", "price": -105, "point": 15.5}, {"name": "Under", "description": "Joey Cantillo", "price": -135, "point": 15.5}]}, {"key": "pitcher_strikeouts", "last_update": "2026-07-07T01:15:27Z", "outcomes": [{"name": "Over", "description": "Joey Cantillo", "price": -145, "point": 4.5}, {"name": "Under", "description": "Joey Cantillo", "price": 110, "point": 4.5}]}]}, {"key": "draftkings", "title": "DraftKings", "markets": [{"key": "pitcher_outs", "last_update": "2026-07-07T01:15:57Z", "outcomes": [{"name": "Over", "description": "Taj Bradley", "price": -104, "point": 16.5}, {"name": "Under", "description": "Taj Bradley", "price": -128, "point": 16.5}, {"name": "Over", "description": "Joey Cantillo", "price": -111, "point": 15.5}, {"name": "Under", "description": "Joey Cantillo", "price": -119, "point": 15.5}]}, {"key": "pitcher_strikeouts", "last_update": "2026-07-07T01:15:57Z", "outcomes": [{"name": "Over", "description": "Taj Bradley", "price": 117, "point": 6.5}, {"name": "Under", "description": "Taj Bradley", "price": -150, "point": 6.5}, {"name": "Over", "description": "Joey Cantillo", "price": -143, "point": 4.5}, {"name": "Under", "description": "Joey Cantillo", "price": 112, "point": 4.5}]}]}, {"key": "bovada", "title": "Bovada", "markets": [{"key": "pitcher_earned_runs", "last_update": "2026-07-07T01:15:49Z", "outcomes": [{"name": "Over", "description": "Joey Cantillo", "price": 100, "point": 2.5}, {"name": "Under", "description": "Joey Cantillo", "price": -140, "point": 2.5}, {"name": "Over", "description": "Taj Bradley", "price": 105, "point": 2.5}, {"name": "Under", "description": "Taj Bradley", "price": -145, "point": 2.5}]}, {"key": "pitcher_outs", "last_update": "2026-07-07T01:15:49Z", "outcomes": [{"name": "Over", "description": "Joey Cantillo", "price": -115, "point": 15.5}, {"name": "Under", "description": "Joey Cantillo", "price": -125, "point": 15.5}, {"name": "Over", "description": "Taj Bradley", "price": -105, "point": 16.5}, {"name": "Under", "description": "Taj Bradley", "price": -135, "point": 16.5}]}, {"key": "pitcher_strikeouts", "last_update": "2026-07-07T01:15:49Z", "outcomes": [{"name": "Over", "description": "Joey Cantillo", "price": -170, "point": 4.5}, {"name": "Under", "description": "Joey Cantillo", "price": 130, "point": 4.5}, {"name": "Over", "description": "Taj Bradley", "price": 120, "point": 6.5}, {"name": "Under", "description": "Taj Bradley", "price": -160, "point": 6.5}]}]}]}, {"id": "c6ef398cb6827a8a660c67c3f3e6dbd5", "sport_key": "baseball_mlb", "sport_title": "MLB", "commence_time": "2026-07-08T00:06:00Z", "home_team": "Texas Rangers", "away_team": "Los Angeles Angels", "bookmakers": []}, {"id": "0ae1e836fd92f0f98b83e2d7451f6f97", "sport_key": "baseball_mlb", "sport_title": "MLB", "commence_time": "2026-07-08T01:46:00Z", "home_team": "San Francisco Giants", "away_team": "Toronto Blue Jays", "bookmakers": []}, {"id": "8df69c8e501590af54db5363e5fdc3af", "sport_key": "baseball_mlb", "sport_title": "MLB", "commence_time": "2026-07-08T02:11:00Z", "home_team": "Los Angeles Dodgers", "away_team": "Colorado Rockies", "bookmakers": [{"key": "fanduel", "title": "FanDuel", "markets": [{"key": "pitcher_strikeouts", "last_update": "2026-07-07T01:15:36Z", "outcomes": [{"name": "Over", "description": "Justin Wrobleski", "price": 102, "point": 5.5}, {"name": "Under", "description": "Justin Wrobleski", "price": -130, "point": 5.5}, {"name": "Over", "description": "Michael Lorenzen", "price": -146, "point": 3.5}, {"name": "Under", "description": "Michael Lorenzen", "price": 114, "point": 3.5}]}]}, {"key": "bovada", "title": "Bovada", "markets": [{"key": "pitcher_strikeouts", "last_update": "2026-07-07T01:15:28Z", "outcomes": [{"name": "Over", "description": "Justin Wrobleski", "price": 100, "point": 5.5}, {"name": "Under", "description": "Justin Wrobleski", "price": -130, "point": 5.5}, {"name": "Over", "description": "Michael Lorenzen", "price": -150, "point": 3.5}, {"name": "Under", "description": "Michael Lorenzen", "price": 115, "point": 3.5}]}]}]}]}